cgapi/__init__.py
cgapi/api.py
cgapi/error.py
climate_guard_api-0.0.4.dist-info/LICENSE
climate_guard_api-0.0.4.dist-info/METADATA
climate_guard_api-0.0.4.dist-info/WHEEL
climate_guard_api-0.0.4.dist-info/top_level.txt
climate_guard_api-0.0.4.dist-info/RECORD
